simple_icons_pack/__init__.py
simple_icons_pack/__init__.pyi
simple_icons_pack/py.typed
simple_icons_pack/simple_icons_pack.abi3.so
simple_icons_pack-16.6.1.dist-info/METADATA
simple_icons_pack-16.6.1.dist-info/WHEEL
simple_icons_pack-16.6.1.dist-info/licenses/LICENSE
simple_icons_pack-16.6.1.dist-info/RECORD
