Metadata-Version: 2.4
Name: simple-icons-pack
Version: 16.6.1
Classifier: Programming Language :: Rust
Classifier: Programming Language :: Python :: Implementation :: CPython
Classifier: Programming Language :: Python :: Implementation :: PyPy
License-File: LICENSE
Summary: A redistribution of simple-icons npm package's SVG and metadata.
License: CC0-1.0
Requires-Python: >=3.8
Project-URL: source, https://github.com/2bndy5/redist-icons
